flipt/__init__.py
flipt/apps.py
flipt/clients.py
flipt/decorators.py
flipt/flags.py
flipt/routers.py
flipt/templatetags/__init__.py
flipt/templatetags/feature_flags.py
flipt/urls.py
flipt/views.py
django_flipt-0.2.4.dist-info/LICENSE
django_flipt-0.2.4.dist-info/WHEEL
django_flipt-0.2.4.dist-info/METADATA
django_flipt-0.2.4.dist-info/RECORD
